tests/__init__.py
tests/test_connection.py
tests/test_connection_details.py
tinyproto/__init__.py
tinyproto/client.py
tinyproto/connection.py
tinyproto/connection_details.py
tinyproto/errors.py
tinyproto/plugins.py
tinyproto/server.py
tinyproto-3.0.dist-info/METADATA
tinyproto-3.0.dist-info/WHEEL
tinyproto-3.0.dist-info/top_level.txt
tinyproto-3.0.dist-info/RECORD
