Metadata-Version: 2.1
Name: tinyproto
Version: 3.0
Summary: Small tcp protocol library
Author-email: Spajderix <spajderix@gmail.com>
Project-URL: Homepage, https://github.com/spajderix/tinyproto
Classifier: Programming Language :: Python :: 3
Classifier: License :: OSI Approved :: GNU Lesser General Public License v3 or later (LGPLv3+)
Classifier: Operating System :: OS Independent
Requires-Python: >=3.6
